oio-streams
pyostreams
