Metadata-Version: 1.0
Name: pyostreams
Version: 0.0.3
Summary: Python interface to ciostreams .
Home-page: UNKNOWN
Author: Angelo Frangione
Author-email: angelo.frangione@openio.io
License: GPL-v2.0
Platform: UNKNOWN
